{
  "rows": [
    {
      "spell_id": "boed_affliction",
      "level": 3
    },
    {
      "spell_id": "boed_axiomatic_creature",
      "level": 8
    },
    {
      "spell_id": "boed_bastion_of_good",
      "level": 7
    },
    {
      "spell_id": "boed_blessed_sight",
      "level": 3
    },
    {
      "spell_id": "boed_blood_of_the_martyr",
      "level": 4
    },
    {
      "spell_id": "boed_call_faithful_servants",
      "level": 6
    },
    {
      "spell_id": "boed_celestial_blood",
      "level": 6
    },
    {
      "spell_id": "boed_celestial_brilliance",
      "level": 4
    },
    {
      "spell_id": "boed_chaav_s_laugh",
      "level": 5
    },
    {
      "spell_id": "boed_convert_wand",
      "level": 5
    },
    {
      "spell_id": "boed_crown_of_brilliance",
      "level": 6
    },
    {
      "spell_id": "boed_crown_of_flame",
      "level": 5
    },
    {
      "spell_id": "boed_dancing_web",
      "level": 5
    },
    {
      "spell_id": "boed_ease_pain",
      "level": 2
    },
    {
      "spell_id": "boed_elation",
      "level": 2
    },
    {
      "spell_id": "boed_end_to_strife",
      "level": 9
    },
    {
      "spell_id": "boed_energetic_healing",
      "level": 5
    },
    {
      "spell_id": "boed_energize_potion",
      "level": 3
    },
    {
      "spell_id": "boed_estanna_s_stew",
      "level": 2
    },
    {
      "spell_id": "boed_eyes_of_the_avoral",
      "level": 1
    },
    {
      "spell_id": "boed_greater_status",
      "level": 4
    },
    {
      "spell_id": "boed_heart_s_ease",
      "level": 3
    },
    {
      "spell_id": "boed_heaven_s_trumpet",
      "level": 7
    },
    {
      "spell_id": "boed_inspired_aim",
      "level": 3
    },
    {
      "spell_id": "boed_lantern_light",
      "level": 1
    },
    {
      "spell_id": "boed_last_judgment",
      "level": 8
    },
    {
      "spell_id": "boed_lastai_s_caress",
      "level": 2
    },
    {
      "spell_id": "boed_quickshift",
      "level": 6
    },
    {
      "spell_id": "boed_ray_of_hope",
      "level": 1
    },
    {
      "spell_id": "boed_remove_addiction",
      "level": 2
    },
    {
      "spell_id": "boed_remove_fatigue",
      "level": 4
    },
    {
      "spell_id": "boed_remove_nausea",
      "level": 3
    },
    {
      "spell_id": "boed_righteous_glare",
      "level": 7
    },
    {
      "spell_id": "boed_righteous_smite",
      "level": 7
    },
    {
      "spell_id": "boed_sacred_guardian",
      "level": 5
    },
    {
      "spell_id": "boed_shield_of_the_archons",
      "level": 7
    },
    {
      "spell_id": "boed_spread_of_contentment",
      "level": 8
    },
    {
      "spell_id": "boed_stars_of_arvandor",
      "level": 4
    },
    {
      "spell_id": "boed_sublime_revelry",
      "level": 9
    },
    {
      "spell_id": "boed_sustain",
      "level": 4
    },
    {
      "spell_id": "boed_sword_of_conscience",
      "level": 4
    },
    {
      "spell_id": "boed_telepathy_block",
      "level": 5
    },
    {
      "spell_id": "boed_tomb_of_light",
      "level": 7
    },
    {
      "spell_id": "boed_touch_of_adamantine",
      "level": 6
    },
    {
      "spell_id": "boed_vengeance_halo",
      "level": 6
    },
    {
      "spell_id": "boed_vision_of_heaven",
      "level": 1
    },
    {
      "spell_id": "boed_warding_gems",
      "level": 5
    }
  ]
}
