{
  "schema_version": "1.0",
  "source": "BoED v3.5",
  "chapter": "Magic",
  "section": "Cleric Spell List (BoED)",
  "fields": [
    "spell_id",
    "level"
  ],
  "rows": [
    {
      "spell_id": "BOED_SPELL_axiomatic_creature",
      "level": 8
    },
    {
      "spell_id": "BOED_SPELL_ayailla_s_radiant_burst",
      "level": 2
    },
    {
      "spell_id": "BOED_SPELL_blood_of_the_martyr",
      "level": 4
    },
    {
      "spell_id": "BOED_SPELL_brilliant_emanation",
      "level": 3
    },
    {
      "spell_id": "BOED_SPELL_call_faithful_servants",
      "level": 6
    },
    {
      "spell_id": "BOED_SPELL_celestial_aspect",
      "level": 3
    },
    {
      "spell_id": "BOED_SPELL_celestial_brilliance",
      "level": 5
    },
    {
      "spell_id": "BOED_SPELL_channel_celestial",
      "level": 7
    },
    {
      "spell_id": "BOED_SPELL_channel_greater_celestial",
      "level": 9
    },
    {
      "spell_id": "BOED_SPELL_constricting_chains",
      "level": 7
    },
    {
      "spell_id": "BOED_SPELL_convert_wand",
      "level": 5
    },
    {
      "spell_id": "BOED_SPELL_cry_of_ysgard",
      "level": 7
    },
    {
      "spell_id": "BOED_SPELL_curtain_of_light",
      "level": 5
    },
    {
      "spell_id": "BOED_SPELL_dancing_web",
      "level": 5
    },
    {
      "spell_id": "BOED_SPELL_diamond_spray",
      "level": 4
    },
    {
      "spell_id": "BOED_SPELL_divine_inspiration",
      "level": 1
    },
    {
      "spell_id": "BOED_SPELL_eladrin_form",
      "level": 2
    },
    {
      "spell_id": "BOED_SPELL_end_to_strife",
      "level": 9
    },
    {
      "spell_id": "BOED_SPELL_energetic_healing",
      "level": 5
    },
    {
      "spell_id": "BOED_SPELL_energize_potion",
      "level": 3
    },
    {
      "spell_id": "BOED_SPELL_estanna_s_stew",
      "level": 2
    },
    {
      "spell_id": "BOED_SPELL_exalted_fury",
      "level": 9
    },
    {
      "spell_id": "BOED_SPELL_greater_status",
      "level": 3
    },
    {
      "spell_id": "BOED_SPELL_heart_s_ease",
      "level": 3
    },
    {
      "spell_id": "BOED_SPELL_heaven_s_trumpet",
      "level": 5
    },
    {
      "spell_id": "BOED_SPELL_inspired_aim",
      "level": 3
    },
    {
      "spell_id": "BOED_SPELL_lantern_light",
      "level": 1
    },
    {
      "spell_id": "BOED_SPELL_last_judgment",
      "level": 8
    },
    {
      "spell_id": "BOED_SPELL_lastai_s_caress",
      "level": 2
    },
    {
      "spell_id": "BOED_SPELL_luminous_armor",
      "level": 2
    },
    {
      "spell_id": "BOED_SPELL_path_of_the_exalted",
      "level": 3
    },
    {
      "spell_id": "BOED_SPELL_phieran_s_resolve",
      "level": 3
    },
    {
      "spell_id": "BOED_SPELL_phoenix_fire",
      "level": 7
    },
    {
      "spell_id": "BOED_SPELL_quickshift",
      "level": 6
    },
    {
      "spell_id": "BOED_SPELL_rain_of_embers",
      "level": 7
    },
    {
      "spell_id": "BOED_SPELL_remove_addiction",
      "level": 2
    },
    {
      "spell_id": "BOED_SPELL_remove_nausea",
      "level": 3
    },
    {
      "spell_id": "BOED_SPELL_restore_soul_s_treasure",
      "level": 8
    },
    {
      "spell_id": "BOED_SPELL_righteous_glare",
      "level": 7
    },
    {
      "spell_id": "BOED_SPELL_sacred_guardian",
      "level": 5
    },
    {
      "spell_id": "BOED_SPELL_sanctify_the_wicked",
      "level": 9
    },
    {
      "spell_id": "BOED_SPELL_secure_corpse",
      "level": 6
    },
    {
      "spell_id": "BOED_SPELL_shield_of_the_archons",
      "level": 7
    },
    {
      "spell_id": "BOED_SPELL_sicken_evil",
      "level": 5
    },
    {
      "spell_id": "BOED_SPELL_spread_of_contentment",
      "level": 8
    },
    {
      "spell_id": "BOED_SPELL_storm_of_shards",
      "level": 6
    },
    {
      "spell_id": "BOED_SPELL_sublime_revelry",
      "level": 9
    },
    {
      "spell_id": "BOED_SPELL_sunmantle",
      "level": 4
    },
    {
      "spell_id": "BOED_SPELL_telepathy_block",
      "level": 5
    },
    {
      "spell_id": "BOED_SPELL_tomb_of_light",
      "level": 7
    },
    {
      "spell_id": "BOED_SPELL_touch_of_adamantine",
      "level": 1
    },
    {
      "spell_id": "BOED_SPELL_valiant_steed",
      "level": 6
    },
    {
      "spell_id": "BOED_SPELL_warding_gems",
      "level": 5
    }
  ]
}
